create_redirect/__init__.py
create_redirect/__main__.py
create_redirect-0.2.1.dist-info/LICENSE
create_redirect-0.2.1.dist-info/METADATA
create_redirect-0.2.1.dist-info/WHEEL
create_redirect-0.2.1.dist-info/entry_points.txt
create_redirect-0.2.1.dist-info/top_level.txt
create_redirect-0.2.1.dist-info/RECORD
