Metadata-Version: 2.1
Name: create-redirect
Version: 0.2.1
Summary: Python script for creating HTML redirects.
Home-page: https://github.com/domdfcoding/create_redirect
Author: Dominic Davis-Foster
Author-email: Dominic Davis-Foster <dominic@davis-foster.co.uk>
License: Copyright (c) 2020 Dominic Davis-Foster
Project-URL: Homepage, https://github.com/domdfcoding/create_redirect
Project-URL: Issue Tracker, https://github.com/domdfcoding/create_redirect/issues
Project-URL: Source Code, https://github.com/domdfcoding/create_redirect
Project-URL: Documentation, https://create-redirect.readthedocs.io/en/latest
Platform: Windows
Platform: macOS
Platform: Linux
Classifier: Development Status :: 3 - Alpha
Classifier: Intended Audience :: Developers
Classifier: License :: OSI Approved :: MIT License
Classifier: Operating System :: OS Independent
Classifier: Programming Language :: Python
Classifier: Programming Language :: Python :: 3 :: Only
Classifier: Programming Language :: Python :: 3.6
Classifier: Programming Language :: Python :: 3.7
Classifier: Programming Language :: Python :: 3.8
Classifier: Programming Language :: Python :: 3.9
Classifier: Programming Language :: Python :: 3.10
Classifier: Programming Language :: Python :: 3.11
Classifier: Programming Language :: Python :: 3.12
Classifier: Programming Language :: Python :: Implementation :: CPython
Classifier: Topic :: Software Development :: Libraries :: Python Modules
Classifier: Topic :: Text Processing :: Markup :: HTML
Requires-Python: >=3.6.1
License-File: LICENSE
